{
  "$schema": "https://developer.microsoft.com/json-schemas/fabric/item/report/definition/visualContainer/2.3.0/schema.json",
  "name": "3c2ee994e68b9e07c827",
  "position": {
    "x": 651.56623252408531,
    "y": 78.409114588866686,
    "z": 7000,
    "height": 240.13802576257561,
    "width": 601.031173051475,
    "tabOrder": 7000
  },
  "visual": {
    "visualType": "clusteredColumnChart",
    "query": {
      "queryState": {
        "Category": {
          "projections": [
            {
              "field": {
                "Column": {
                  "Expression": {
                    "SourceRef": {
                      "Entity": "Weather"
                    }
                  },
                  "Property": "District"
                }
              },
              "queryRef": "Weather.District",
              "nativeQueryRef": "District",
              "active": true
            }
          ]
        },
        "Y": {
          "projections": [
            {
              "field": {
                "Measure": {
                  "Expression": {
                    "SourceRef": {
                      "Entity": "Weather"
                    }
                  },
                  "Property": "Avg Min Wind (Kmph)"
                }
              },
              "queryRef": "Weather.Avg Min Wind (Kmph)",
              "nativeQueryRef": "Avg Min Wind (Kmph)"
            },
            {
              "field": {
                "Measure": {
                  "Expression": {
                    "SourceRef": {
                      "Entity": "Weather"
                    }
                  },
                  "Property": "Avg Max Wind (Kmph)"
                }
              },
              "queryRef": "Weather.Avg Max Wind (Kmph)",
              "nativeQueryRef": "Avg Max Wind (Kmph)"
            }
          ]
        }
      },
      "sortDefinition": {
        "sort": [
          {
            "field": {
              "Measure": {
                "Expression": {
                  "SourceRef": {
                    "Entity": "Weather"
                  }
                },
                "Property": "Avg Min Wind (Kmph)"
              }
            },
            "direction": "Descending"
          }
        ],
        "isDefaultSort": true
      }
    },
    "objects": {
      "legend": [
        {
          "properties": {
            "show": {
              "expr": {
                "Literal": {
                  "Value": "true"
                }
              }
            },
            "showTitle": {
              "expr": {
                "Literal": {
                  "Value": "false"
                }
              }
            },
            "bold": {
              "expr": {
                "Literal": {
                  "Value": "true"
                }
              }
            },
            "labelColor": {
              "solid": {
                "color": {
                  "expr": {
                    "Literal": {
                      "Value": "'#f0e199'"
                    }
                  }
                }
              }
            }
          }
        }
      ],
      "categoryAxis": [
        {
          "properties": {
            "fontSize": {
              "expr": {
                "Literal": {
                  "Value": "8D"
                }
              }
            },
            "bold": {
              "expr": {
                "Literal": {
                  "Value": "true"
                }
              }
            },
            "labelColor": {
              "solid": {
                "color": {
                  "expr": {
                    "Literal": {
                      "Value": "'#FFF9AF'"
                    }
                  }
                }
              }
            },
            "showAxisTitle": {
              "expr": {
                "Literal": {
                  "Value": "false"
                }
              }
            }
          }
        }
      ],
      "valueAxis": [
        {
          "properties": {
            "bold": {
              "expr": {
                "Literal": {
                  "Value": "true"
                }
              }
            },
            "labelColor": {
              "solid": {
                "color": {
                  "expr": {
                    "Literal": {
                      "Value": "'#FFF9AF'"
                    }
                  }
                }
              }
            },
            "showAxisTitle": {
              "expr": {
                "Literal": {
                  "Value": "false"
                }
              }
            },
            "gridlineShow": {
              "expr": {
                "Literal": {
                  "Value": "false"
                }
              }
            }
          }
        }
      ],
      "labels": [
        {
          "properties": {
            "labelPrecision": {
              "expr": {
                "Literal": {
                  "Value": "2L"
                }
              }
            },
            "show": {
              "expr": {
                "Literal": {
                  "Value": "true"
                }
              }
            },
            "enableBackground": {
              "expr": {
                "Literal": {
                  "Value": "true"
                }
              }
            },
            "color": {
              "solid": {
                "color": {
                  "expr": {
                    "Literal": {
                      "Value": "'#FFF9AF'"
                    }
                  }
                }
              }
            },
            "backgroundColor": {
              "solid": {
                "color": {
                  "expr": {
                    "Literal": {
                      "Value": "'#042F4C'"
                    }
                  }
                }
              }
            },
            "backgroundTransparency": {
              "expr": {
                "Literal": {
                  "Value": "50L"
                }
              }
            }
          }
        }
      ],
      "zoom": [
        {
          "properties": {
            "show": {
              "expr": {
                "Literal": {
                  "Value": "false"
                }
              }
            }
          }
        }
      ],
      "dataPoint": [
        {
          "properties": {
            "fill": {
              "solid": {
                "color": {
                  "expr": {
                    "Literal": {
                      "Value": "'#D2750E'"
                    }
                  }
                }
              }
            }
          },
          "selector": {
            "metadata": "Weather.Avg Min Temp (°C)"
          }
        },
        {
          "properties": {
            "fill": {
              "solid": {
                "color": {
                  "expr": {
                    "ThemeDataColor": {
                      "ColorId": 8,
                      "Percent": 0.6
                    }
                  }
                }
              }
            }
          },
          "selector": {
            "metadata": "Weather.Avg Max Temp (°C)"
          }
        },
        {
          "properties": {
            "fill": {
              "solid": {
                "color": {
                  "expr": {
                    "Literal": {
                      "Value": "'#FF7D29'"
                    }
                  }
                }
              }
            },
            "borderShow": {
              "expr": {
                "Literal": {
                  "Value": "true"
                }
              }
            },
            "borderColor": {
              "solid": {
                "color": {
                  "expr": {
                    "Literal": {
                      "Value": "'#FFF1F1'"
                    }
                  }
                }
              }
            },
            "borderSize": {
              "expr": {
                "Literal": {
                  "Value": "2D"
                }
              }
            }
          }
        },
        {
          "properties": {
            "fill": {
              "solid": {
                "color": {
                  "expr": {
                    "ThemeDataColor": {
                      "ColorId": 8,
                      "Percent": 0.6
                    }
                  }
                }
              }
            }
          },
          "selector": {
            "data": [
              {
                "scopeId": {
                  "Comparison": {
                    "ComparisonKind": 0,
                    "Left": {
                      "Column": {
                        "Expression": {
                          "SourceRef": {
                            "Entity": "Weather"
                          }
                        },
                        "Property": "District"
                      }
                    },
                    "Right": {
                      "Literal": {
                        "Value": "'Bhadradri Kothagudem'"
                      }
                    }
                  }
                }
              }
            ]
          }
        },
        {
          "properties": {
            "fill": {
              "solid": {
                "color": {
                  "expr": {
                    "Literal": {
                      "Value": "'#FF7D29'"
                    }
                  }
                }
              }
            }
          },
          "selector": {
            "data": [
              {
                "scopeId": {
                  "Comparison": {
                    "ComparisonKind": 0,
                    "Left": {
                      "Column": {
                        "Expression": {
                          "SourceRef": {
                            "Entity": "Weather"
                          }
                        },
                        "Property": "District"
                      }
                    },
                    "Right": {
                      "Literal": {
                        "Value": "'Nizamabad'"
                      }
                    }
                  }
                }
              }
            ]
          }
        },
        {
          "properties": {
            "fill": {
              "solid": {
                "color": {
                  "expr": {
                    "ThemeDataColor": {
                      "ColorId": 8,
                      "Percent": 0.6
                    }
                  }
                }
              }
            }
          },
          "selector": {
            "metadata": "Weather.Humidity Z-Score"
          }
        },
        {
          "properties": {
            "fill": {
              "solid": {
                "color": {
                  "expr": {
                    "ThemeDataColor": {
                      "ColorId": 8,
                      "Percent": 0.6
                    }
                  }
                }
              }
            }
          },
          "selector": {
            "metadata": "Weather.Avg Min Wind (Kmph)"
          }
        },
        {
          "properties": {
            "fill": {
              "solid": {
                "color": {
                  "expr": {
                    "Literal": {
                      "Value": "'#33A1E0'"
                    }
                  }
                }
              }
            }
          },
          "selector": {
            "metadata": "Weather.Avg Max Wind (Kmph)"
          }
        },
        {
          "properties": {
            "fill": {
              "solid": {
                "color": {
                  "expr": {
                    "Literal": {
                      "Value": "'#33A1E0'"
                    }
                  }
                }
              }
            }
          },
          "selector": {
            "data": [
              {
                "scopeId": {
                  "Comparison": {
                    "ComparisonKind": 0,
                    "Left": {
                      "Column": {
                        "Expression": {
                          "SourceRef": {
                            "Entity": "Weather"
                          }
                        },
                        "Property": "Wind Outlier Flag"
                      }
                    },
                    "Right": {
                      "Literal": {
                        "Value": "'Normal'"
                      }
                    }
                  }
                }
              }
            ]
          }
        },
        {
          "properties": {
            "fill": {
              "solid": {
                "color": {
                  "expr": {
                    "Literal": {
                      "Value": "'#1677B7'"
                    }
                  }
                }
              }
            }
          },
          "selector": {
            "data": [
              {
                "scopeId": {
                  "Comparison": {
                    "ComparisonKind": 0,
                    "Left": {
                      "Column": {
                        "Expression": {
                          "SourceRef": {
                            "Entity": "Weather"
                          }
                        },
                        "Property": "Wind Outlier Flag"
                      }
                    },
                    "Right": {
                      "Literal": {
                        "Value": "'Very High'"
                      }
                    }
                  }
                }
              }
            ]
          }
        }
      ]
    },
    "visualContainerObjects": {
      "title": [
        {
          "properties": {
            "text": {
              "expr": {
                "Literal": {
                  "Value": "'Average Min & Max Wind Speed by District'"
                }
              }
            },
            "titleWrap": {
              "expr": {
                "Literal": {
                  "Value": "true"
                }
              }
            },
            "fontColor": {
              "solid": {
                "color": {
                  "expr": {
                    "Literal": {
                      "Value": "'#f0e199'"
                    }
                  }
                }
              }
            },
            "alignment": {
              "expr": {
                "Literal": {
                  "Value": "'center'"
                }
              }
            },
            "heading": {
              "expr": {
                "Literal": {
                  "Value": "'Heading2'"
                }
              }
            }
          }
        }
      ],
      "background": [
        {
          "properties": {
            "show": {
              "expr": {
                "Literal": {
                  "Value": "true"
                }
              }
            },
            "color": {
              "solid": {
                "color": {
                  "expr": {
                    "Literal": {
                      "Value": "'#084872'"
                    }
                  }
                }
              }
            },
            "transparency": {
              "expr": {
                "Literal": {
                  "Value": "0D"
                }
              }
            }
          }
        }
      ],
      "border": [
        {
          "properties": {
            "show": {
              "expr": {
                "Literal": {
                  "Value": "true"
                }
              }
            },
            "color": {
              "solid": {
                "color": {
                  "expr": {
                    "Literal": {
                      "Value": "'#33A1E0'"
                    }
                  }
                }
              }
            },
            "radius": {
              "expr": {
                "Literal": {
                  "Value": "30D"
                }
              }
            },
            "width": {
              "expr": {
                "Literal": {
                  "Value": "3D"
                }
              }
            }
          }
        }
      ],
      "dropShadow": [
        {
          "properties": {
            "show": {
              "expr": {
                "Literal": {
                  "Value": "true"
                }
              }
            }
          }
        }
      ],
      "visualTooltip": [
        {
          "properties": {
            "themedBackground": {
              "solid": {
                "color": {
                  "expr": {
                    "Literal": {
                      "Value": "'#042F4C'"
                    }
                  }
                }
              }
            },
            "themedTitleFontColor": {
              "solid": {
                "color": {
                  "expr": {
                    "Literal": {
                      "Value": "'#f0e199'"
                    }
                  }
                }
              }
            },
            "themedValueFontColor": {
              "solid": {
                "color": {
                  "expr": {
                    "Literal": {
                      "Value": "'#FFEB96'"
                    }
                  }
                }
              }
            }
          }
        }
      ]
    },
    "drillFilterOtherVisuals": true
  },
  "parentGroupName": "341b7c9e6c0ca2b7dc2b",
  "filterConfig": {
    "filters": [
      {
        "name": "ec943955841d56f05af4",
        "field": {
          "Column": {
            "Expression": {
              "SourceRef": {
                "Entity": "Weather"
              }
            },
            "Property": "District"
          }
        },
        "type": "TopN",
        "filter": {
          "Version": 2,
          "From": [
            {
              "Name": "subquery",
              "Expression": {
                "Subquery": {
                  "Query": {
                    "Version": 2,
                    "From": [
                      {
                        "Name": "w",
                        "Entity": "Weather",
                        "Type": 0
                      }
                    ],
                    "Select": [
                      {
                        "Column": {
                          "Expression": {
                            "SourceRef": {
                              "Source": "w"
                            }
                          },
                          "Property": "District"
                        },
                        "Name": "field"
                      }
                    ],
                    "OrderBy": [
                      {
                        "Direction": 2,
                        "Expression": {
                          "Measure": {
                            "Expression": {
                              "SourceRef": {
                                "Source": "w"
                              }
                            },
                            "Property": "Avg Max Wind (Kmph)"
                          }
                        }
                      }
                    ],
                    "Top": 3
                  }
                }
              },
              "Type": 2
            },
            {
              "Name": "w",
              "Entity": "Weather",
              "Type": 0
            }
          ],
          "Where": [
            {
              "Condition": {
                "In": {
                  "Expressions": [
                    {
                      "Column": {
                        "Expression": {
                          "SourceRef": {
                            "Source": "w"
                          }
                        },
                        "Property": "District"
                      }
                    }
                  ],
                  "Table": {
                    "SourceRef": {
                      "Source": "subquery"
                    }
                  }
                }
              }
            }
          ]
        }
      },
      {
        "name": "831762425695161fef7e",
        "field": {
          "Measure": {
            "Expression": {
              "SourceRef": {
                "Entity": "Weather"
              }
            },
            "Property": "Avg Min Wind (Kmph)"
          }
        },
        "type": "Advanced"
      },
      {
        "name": "b56ace169f19903bdea8",
        "field": {
          "Measure": {
            "Expression": {
              "SourceRef": {
                "Entity": "Weather"
              }
            },
            "Property": "Avg Max Wind (Kmph)"
          }
        },
        "type": "Advanced"
      }
    ]
  }
}